<?xml version="1.0" encoding="ISO-8859-1"?>
<auto-update><file><uri>Documentação/Logica dos modais.txt</uri><size>1745</size></file><file><uri>Documentação/auto-include e mapeamento de classes.txt</uri><size>1532</size></file><file><uri>Documentação/class.login.txt</uri><size>641</size></file><file><uri>Documentação/cms.notifications.txt</uri><size>592</size></file><file><uri>Documentação/cms.sessions.txt</uri><size>1943</size></file><file><uri>Documentação/estrutura de pastas.txt</uri><size>515</size></file><file><uri>Documentação/methods pkw.function.txt</uri><size>365</size></file><file><uri>Documentação/musicas para baixar.txt</uri><size>33</size></file><file><uri>Documentação/questoes.txt</uri><size>261</size></file><file><uri>Documentação/types.sessions.txt</uri><size>259</size></file><file><uri>configs/auto.update.xml</uri><size>2982</size></file><file><uri>controller/0routes.php</uri><size>7761</size></file><file><uri>controller/routes.php</uri><size>8881</size></file><file><uri>exceltojason/LICENCE.txt</uri><size>954</size></file><file><uri>exceltojason/excelMap.class.php</uri><size>11479</size></file><file><uri>exceltojason/osmani.xlsx</uri><size>2038997</size></file><file><uri>exceltojason/print_filter_cells.php</uri><size>296</size></file><file><uri>exceltojason/print_filter_data.php</uri><size>295</size></file><file><uri>exceltojason/print_sheet_cells.php</uri><size>188</size></file><file><uri>exceltojason/print_sheet_data.php</uri><size>188</size></file><file><uri>exceltojason/print_sheet_rows.php</uri><size>187</size></file><file><uri>exceltojason/print_sheets.php</uri><size>136</size></file><file><uri>exceltojason/test.php</uri><size>299</size></file><file><uri>exceltojason/timeHelper.php</uri><size>1490</size></file><file><uri>libs/PHPExcel.php</uri><size>31446</size></file><file><uri>libs/SpreadsheetReader.php</uri><size>8653</size></file><file><uri>libs/SpreadsheetReader_CSV.php</uri><size>7050</size></file><file><uri>libs/SpreadsheetReader_ODS.php</uri><size>8187</size></file><file><uri>libs/SpreadsheetReader_XLS.php</uri><size>5923</size></file><file><uri>libs/SpreadsheetReader_XLSX.php</uri><size>29723</size></file><file><uri>libs/autoUpdate.php</uri><size>2688</size></file><file><uri>libs/excel_reader2.php</uri><size>57845</size></file><file><uri>libs/file.php</uri><size>1958</size></file><file><uri>libs/functions.php</uri><size>12090</size></file><file><uri>libs/login.php</uri><size>444</size></file><file><uri>libs/phplot-6.1.0</uri><size>4096</size></file><file><uri>libs/user.php</uri><size>892</size></file><file><uri>libs/util.php</uri><size>1494</size></file><file><uri>models/database.php</uri><size>3209</size></file><file><uri>old/envia.php</uri><size>776</size></file><file><uri>old/index.html</uri><size>6771</size></file><file><uri>old/moline.sql</uri><size>3008662</size></file><file><uri>vendor/autoload.php</uri><size>183</size></file><file><uri>xls/05MAI.xlsx</uri><size>131072</size></file><file><uri>xls/07jul.xlsx</uri><size>180224</size></file></auto-update>
